[
    {
        "title": "Convention Communique du CongrEs",
        "page_numbers": [
            "55"
        ]
    },
    {
        "title": "2019 RCNA Educational Symposium",
        "page_numbers": [
            "56"
        ]
    },
    {
        "title": "2019 RCNA Convention Program of Events \u2022 CongrEs de l'ARNC 2019 Programme des ActivitEs",
        "page_numbers": [
            "59"
        ]
    },
    {
        "title": "Undocumented Variety of Breton 886 \u2022 Nouvelle variEtE de Breton 886 par/by ClEment Chapados-Girard, lm #451",
        "page_numbers": [
            "64"
        ]
    },
    {
        "title": "Numismatic History - The Battle of Munda by Jesljs Vico and Marisa Ollero",
        "page_numbers": [
            "67"
        ]
    },
    {
        "title": "2019 RCNA Annual Convention Registration Form \u2022 CongrEs annuel de l'ARNC 2019 Formulaire d'enregistrement",
        "page_numbers": [
            "71"
        ]
    },
    {
        "title": "The March of Dimes and the Polio Vaccine by Ellison Roth",
        "page_numbers": [
            "76"
        ]
    },
    {
        "title": "2019 Coin of the Year Winners Announced",
        "page_numbers": [
            "84"
        ]
    },
    {
        "title": "From the President \u2022 Mot du President 69,70....................................................................................In the News by Henry Nienhuis, frcna, fcnrs, fona, lm #430",
        "page_numbers": [
            "53"
        ]
    },
    {
        "title": "In the News by Henry Nienhuis, frcna, fcnrs, fona, lm #430",
        "page_numbers": [
            "69","70"
        ]
    },
    {
        "title": "News From the Clubs \u2022 Nouvelles des Clubs by Brett Irick, Club Services, FONA, #22198",
        "page_numbers": [
            "75"
        ]
    },
    {
        "title": "Coming Events",
        "page_numbers": [
            "80"
        ]
    },
    {
        "title": "Report of the Executive Secretary \u2022 Rapport du Secretaire exEcutif",
        "page_numbers": [
            "82"
        ]
    },
    {
        "title": "Royal Canadian Mint Communique",
        "page_numbers": [
            "88"
        ]
    },
    {
        "title": "RCNA Member Dealer Directory",
        "page_numbers": [
            "90"
        ]
    },
    {
        "title": "Book Review by Serge Pelletier LM #423",
        "page_numbers": [
            "92"
        ]
    },
    {
        "title": "RoyAl Writings by Alan Roy, #17134 51",
        "page_numbers": [
            "94"
        ]
    }
]